CHANGES.txt
README.md
setup.py
djinn_search/__init__.py
djinn_search/urls.py
djinn_search/utils.py
djinn_search.egg-info/PKG-INFO
djinn_search.egg-info/SOURCES.txt
djinn_search.egg-info/dependency_links.txt
djinn_search.egg-info/entry_points.txt
djinn_search.egg-info/not-zip-safe
djinn_search.egg-info/requires.txt
djinn_search.egg-info/top_level.txt
djinn_search/fields/__init__.py
djinn_search/fields/contenttype.py
djinn_search/forms/__init__.py
djinn_search/forms/base.py
djinn_search/forms/groupcontent.py
djinn_search/forms/usercontent.py
djinn_search/locale/nl_NL/LC_MESSAGES/django.po
djinn_search/templates/djinn_search/search.html
djinn_search/views/__init__.py
djinn_search/views/base.py
djinn_search/widgets/__init__.py
djinn_search/widgets/contenttype.py