Metadata-Version: 1.1
Name: djinn-search
Version: 1.0.4
Summary: Djinn Intranet search module
Home-page: https://github.com/PythonUnited/djinn_search
Author: PythonUnited
Author-email: info@pythonunited.com
License: beer-ware
Keywords: Djinn Django intranet
Platform: UNKNOWN
Classifier: Development Status :: 3 - Alpha
Classifier: Framework :: Django
Classifier: Intended Audience :: Developers
Classifier: License :: Freely Distributable
Classifier: Programming Language :: Python
Classifier: Topic :: Internet :: WWW/HTTP :: Site Management
Classifier: Topic :: Software Development :: Libraries :: Application Frameworks
